Stock_WeChat
