Metadata-Version: 1.1
Name: Stock-WeChat
Version: 0.1.2
Summary: Set up WeChat reminder of a targeted stock
Home-page: http://ipreacher.github.io
Author: ipreacher
Author-email: ipreacher@hotmail.com
License: MIT License
Keywords: stock,WeChat
Platform: UNKNOWN
Classifier: Development Status :: 3 - Alpha
Classifier: Intended Audience :: Developers
Classifier: Topic :: Software Development :: Libraries
Classifier: License :: OSI Approved :: MIT License
Classifier: Programming Language :: Python :: 3.5
Classifier: Programming Language :: Python :: 3.6
